Metadata-Version: 1.1
Name: shoogle
Version: 0.1.0
Summary: Google API from the command line
Home-page: https://github.com/tokland/shoogle
Author: Arnau Sanchez
Author-email: pyarnau@gmail.com
License: ISCL
Keywords: shoogle
Platform: UNKNOWN
Classifier: Development Status :: 4 - Beta
Classifier: Intended Audience :: End Users/Desktop
Classifier: License :: OSI Approved :: GNU General Public License (GPL)
Classifier: Natural Language :: English
Classifier: Operating System :: POSIX
Classifier: Operating System :: Microsoft :: Windows
Classifier: Topic :: Internet :: WWW/HTTP
Classifier: Programming Language :: Python :: 3
Classifier: Programming Language :: Python :: 3.3
Classifier: Programming Language :: Python :: 3.4
Classifier: Programming Language :: Python :: 3.5
